{
  "resourceType": "StructureDefinition",
  "id": "mii-pr-seltene-therapieempfehlung-nicht-medikamentoes",
  "url": "https://www.medizininformatik-initiative.de/fhir/ext/modul-seltene/StructureDefinition/mii-pr-seltene-therapieempfehlung-nicht-medikamentoes",
  "version": "2026.0.0-ballot",
  "name": "MII_PR_Seltene_TherapieempfehlungNichtMedikamentoes",
  "title": "MII PR SE Therapieempfehlung Nicht-Medikamentös",
  "status": "draft",
  "publisher": "Medizininformatik Initiative",
  "contact": [
    {
      "telecom": [
        {
          "system": "url",
          "value": "https://www.medizininformatik-initiative.de"
        }
      ]
    }
  ],
  "description": "Therapieempfehlung für nicht-medikamentöse Interventionen bei seltenen Erkrankungen (z.B. Ernährungstherapie, Gentherapie, Prophylaxe, Früherkennung)",
  "fhirVersion": "4.0.1",
  "kind": "resource",
  "abstract": false,
  "type": "ServiceRequest",
  "baseDefinition": "http://hl7.org/fhir/StructureDefinition/ServiceRequest",
  "derivation": "constraint",
  "differential": {
    "element": [
      {
        "id": "ServiceRequest.extension:Prioritaet",
        "path": "ServiceRequest.extension",
        "sliceName": "Prioritaet",
        "min": 0,
        "max": "1",
        "type": [
          {
            "code": "Extension",
            "profile": [
              "https://www.medizininformatik-initiative.de/fhir/ext/modul-seltene/StructureDefinition/mii-ex-seltene-empfehlung-prioritaet"
            ]
          }
        ],
        "mustSupport": true
      },
      {
        "id": "ServiceRequest.extension:Evidenzgraduierung",
        "path": "ServiceRequest.extension",
        "sliceName": "Evidenzgraduierung",
        "min": 0,
        "max": "1",
        "type": [
          {
            "code": "Extension",
            "profile": [
              "https://www.medizininformatik-initiative.de/fhir/ext/modul-seltene/StructureDefinition/mii-ex-seltene-empfehlung-evidenzgraduierung"
            ]
          }
        ],
        "mustSupport": true
      },
      {
        "id": "ServiceRequest.extension:Publikation",
        "path": "ServiceRequest.extension",
        "sliceName": "Publikation",
        "min": 0,
        "max": "*",
        "type": [
          {
            "code": "Extension",
            "profile": [
              "https://www.medizininformatik-initiative.de/fhir/ext/modul-seltene/StructureDefinition/mii-ex-seltene-empfehlung-publikation"
            ]
          }
        ],
        "mustSupport": true
      },
      {
        "id": "ServiceRequest.status",
        "path": "ServiceRequest.status",
        "definition": "Status der Umsetzung der nicht-medikamentösen Therapieempfehlung",
        "comment": "draft: Nicht umgesetzt, active: In Umsetzung, completed: Abgeschlossen",
        "mustSupport": true
      },
      {
        "id": "ServiceRequest.intent",
        "path": "ServiceRequest.intent",
        "short": "proposal",
        "definition": "Da es sich um Empfehlungen handelt, wird hier 'proposal' verwendet",
        "patternCode": "proposal",
        "mustSupport": true
      },
      {
        "id": "ServiceRequest.category",
        "path": "ServiceRequest.category",
        "slicing": {
          "discriminator": [
            {
              "type": "pattern",
              "path": "$this"
            }
          ],
          "rules": "open",
          "description": "Slice für Therapiestrategie-Kategorisierung aus Modellvorhaben GenomSeq"
        },
        "min": 1,
        "mustSupport": true
      },
      {
        "id": "ServiceRequest.category:MVGenomSeqTherapieStrategie",
        "path": "ServiceRequest.category",
        "sliceName": "MVGenomSeqTherapieStrategie",
        "short": "Modellvorhaben GenomSeq Therapiestrategie-Typ (Nicht-Medikamentös)",
        "definition": "Kategorisierung der nicht-medikamentösen Therapieempfehlung nach Modellvorhaben GenomSeq",
        "comment": "Dieses Feld ist spezifisch für die Integration mit Modellvorhaben GenomSeq. Es ermöglicht die Kategorisierung gemäß RareDiseasesPlan.recommendedTherapies.strategy. Nur für nicht-medikamentöse Strategien: prophylactic, early-detection, nutrition, other.",
        "min": 0,
        "max": "1",
        "mustSupport": true,
        "binding": {
          "strength": "required",
          "valueSet": "https://www.medizininformatik-initiative.de/fhir/ext/modul-seltene/ValueSet/mii-vs-seltene-therapieempfehlung-strategie-nicht-medikamentoes"
        }
      },
      {
        "id": "ServiceRequest.category:MVGenomSeqTherapieStrategie.coding",
        "path": "ServiceRequest.category.coding",
        "min": 1,
        "max": "1"
      },
      {
        "id": "ServiceRequest.category:MVGenomSeqTherapieStrategie.coding.system",
        "path": "ServiceRequest.category.coding.system",
        "min": 1
      },
      {
        "id": "ServiceRequest.category:MVGenomSeqTherapieStrategie.coding.code",
        "path": "ServiceRequest.category.coding.code",
        "min": 1
      },
      {
        "id": "ServiceRequest.priority",
        "path": "ServiceRequest.priority",
        "definition": "Dringlichkeit der Therapieempfehlung",
        "mustSupport": true
      },
      {
        "id": "ServiceRequest.code",
        "path": "ServiceRequest.code",
        "short": "Art der nicht-medikamentösen Intervention",
        "definition": "Spezifische Codierung der empfohlenen nicht-medikamentösen Therapie",
        "min": 1,
        "mustSupport": true
      },
      {
        "id": "ServiceRequest.code.coding",
        "path": "ServiceRequest.code.coding",
        "slicing": {
          "discriminator": [
            {
              "type": "pattern",
              "path": "system"
            }
          ],
          "rules": "open"
        }
      },
      {
        "id": "ServiceRequest.code.coding:snomed",
        "path": "ServiceRequest.code.coding",
        "sliceName": "snomed",
        "min": 0,
        "max": "1",
        "mustSupport": true,
        "binding": {
          "strength": "extensible",
          "valueSet": "http://hl7.org/fhir/ValueSet/procedure-code"
        }
      },
      {
        "id": "ServiceRequest.code.coding:snomed.system",
        "path": "ServiceRequest.code.coding.system",
        "min": 1,
        "patternUri": "http://snomed.info/sct"
      },
      {
        "id": "ServiceRequest.code.coding:ops",
        "path": "ServiceRequest.code.coding",
        "sliceName": "ops",
        "min": 0,
        "max": "1",
        "mustSupport": true,
        "binding": {
          "strength": "extensible",
          "valueSet": "http://fhir.de/ValueSet/bfarm/ops"
        }
      },
      {
        "id": "ServiceRequest.code.coding:ops.system",
        "path": "ServiceRequest.code.coding.system",
        "min": 1,
        "patternUri": "http://fhir.de/CodeSystem/bfarm/ops"
      },
      {
        "id": "ServiceRequest.code.coding:loinc",
        "path": "ServiceRequest.code.coding",
        "sliceName": "loinc",
        "min": 0,
        "max": "1",
        "mustSupport": true
      },
      {
        "id": "ServiceRequest.code.coding:loinc.system",
        "path": "ServiceRequest.code.coding.system",
        "min": 1,
        "patternUri": "http://loinc.org"
      },
      {
        "id": "ServiceRequest.code.text",
        "path": "ServiceRequest.code.text",
        "min": 1,
        "mustSupport": true
      },
      {
        "id": "ServiceRequest.subject",
        "path": "ServiceRequest.subject",
        "short": "Patient, für den die Therapie empfohlen wird",
        "type": [
          {
            "code": "Reference",
            "targetProfile": [
              "http://hl7.org/fhir/StructureDefinition/Patient"
            ]
          }
        ],
        "mustSupport": true
      },
      {
        "id": "ServiceRequest.encounter",
        "path": "ServiceRequest.encounter",
        "short": "Behandlungskontext der Empfehlung",
        "mustSupport": true
      },
      {
        "id": "ServiceRequest.occurrence[x]",
        "path": "ServiceRequest.occurrence[x]",
        "short": "Empfohlener Zeitpunkt oder Zeitraum für die Intervention",
        "mustSupport": true
      },
      {
        "id": "ServiceRequest.requester",
        "path": "ServiceRequest.requester",
        "short": "Empfehlender Arzt/Einrichtung",
        "type": [
          {
            "code": "Reference",
            "targetProfile": [
              "http://hl7.org/fhir/StructureDefinition/Practitioner",
              "http://hl7.org/fhir/StructureDefinition/PractitionerRole",
              "http://hl7.org/fhir/StructureDefinition/Organization"
            ]
          }
        ],
        "mustSupport": true
      },
      {
        "id": "ServiceRequest.performer",
        "path": "ServiceRequest.performer",
        "short": "Vorgesehener Durchführender der Intervention",
        "mustSupport": true
      },
      {
        "id": "ServiceRequest.reasonCode",
        "path": "ServiceRequest.reasonCode",
        "short": "Grund für die Therapieempfehlung (codiert)",
        "mustSupport": true
      },
      {
        "id": "ServiceRequest.reasonReference",
        "path": "ServiceRequest.reasonReference",
        "short": "Verweis auf zugrundeliegende Diagnose oder Befund",
        "type": [
          {
            "code": "Reference",
            "targetProfile": [
              "http://hl7.org/fhir/StructureDefinition/Condition",
              "http://hl7.org/fhir/StructureDefinition/Observation",
              "http://hl7.org/fhir/StructureDefinition/DiagnosticReport"
            ]
          }
        ],
        "mustSupport": true
      },
      {
        "id": "ServiceRequest.supportingInfo",
        "path": "ServiceRequest.supportingInfo",
        "short": "Unterstützende Informationen zur Empfehlung",
        "type": [
          {
            "code": "Reference",
            "targetProfile": [
              "http://hl7.org/fhir/StructureDefinition/DocumentReference",
              "http://hl7.org/fhir/StructureDefinition/Observation",
              "http://hl7.org/fhir/StructureDefinition/DiagnosticReport"
            ]
          }
        ],
        "mustSupport": true
      },
      {
        "id": "ServiceRequest.note",
        "path": "ServiceRequest.note",
        "short": "Zusätzliche Anmerkungen zur Therapieempfehlung",
        "mustSupport": true
      }
    ]
  }
}
