{
  "resourceType": "StructureDefinition",
  "id": "mii-ex-seltene-tod-durch-seltene-erkrankung",
  "url": "https://www.medizininformatik-initiative.de/fhir/ext/modul-seltene/StructureDefinition/mii-ex-seltene-tod-durch-seltene-erkrankung",
  "version": "2026.0.0-ballot",
  "name": "MII_EX_Seltene_TodDurchSelteneErkrankung",
  "title": "MII EX Seltene Erkrankungen Tod durch Seltene Erkrankung",
  "status": "active",
  "experimental": false,
  "publisher": "Medizininformatik Initiative",
  "contact": [
    {
      "telecom": [
        {
          "system": "url",
          "value": "https://www.medizininformatik-initiative.de"
        }
      ]
    }
  ],
  "description": "Extension zur Dokumentation, ob der Tod des Patienten durch eine seltene Erkrankung verursacht wurde",
  "fhirVersion": "4.0.1",
  "kind": "complex-type",
  "abstract": false,
  "context": [
    {
      "expression": "Patient.deceased[x]",
      "type": "element"
    }
  ],
  "type": "Extension",
  "baseDefinition": "http://hl7.org/fhir/StructureDefinition/Extension",
  "derivation": "constraint",
  "differential": {
    "element": [
      {
        "id": "Extension",
        "path": "Extension",
        "short": "Tod durch seltene Erkrankung",
        "definition": "Gibt an, ob der Patient an einer seltenen Erkrankung verstorben ist"
      },
      {
        "id": "Extension.extension",
        "path": "Extension.extension",
        "min": 1
      },
      {
        "id": "Extension.extension:causedByRareDisease",
        "path": "Extension.extension",
        "sliceName": "causedByRareDisease",
        "short": "Tod durch seltene Erkrankung",
        "definition": "Boolescher Wert, der angibt, ob der Tod durch eine seltene Erkrankung verursacht wurde",
        "min": 1,
        "max": "1",
        "mustSupport": true
      },
      {
        "id": "Extension.extension:causedByRareDisease.extension",
        "path": "Extension.extension.extension",
        "max": "0"
      },
      {
        "id": "Extension.extension:causedByRareDisease.url",
        "path": "Extension.extension.url",
        "fixedUri": "causedByRareDisease"
      },
      {
        "id": "Extension.extension:causedByRareDisease.value[x]",
        "path": "Extension.extension.value[x]",
        "min": 1,
        "type": [
          {
            "code": "boolean"
          }
        ],
        "mustSupport": true
      },
      {
        "id": "Extension.extension:condition",
        "path": "Extension.extension",
        "sliceName": "condition",
        "short": "Verursachende seltene Erkrankung",
        "definition": "Referenz auf die seltene Erkrankung, die zum Tod geführt hat",
        "min": 0,
        "max": "*",
        "mustSupport": true
      },
      {
        "id": "Extension.extension:condition.extension",
        "path": "Extension.extension.extension",
        "max": "0"
      },
      {
        "id": "Extension.extension:condition.url",
        "path": "Extension.extension.url",
        "fixedUri": "condition"
      },
      {
        "id": "Extension.extension:condition.value[x]",
        "path": "Extension.extension.value[x]",
        "min": 1,
        "type": [
          {
            "code": "Reference",
            "targetProfile": [
              "https://www.medizininformatik-initiative.de/fhir/ext/modul-seltene/StructureDefinition/mii-pr-seltene-clinical-diagnosis",
              "https://www.medizininformatik-initiative.de/fhir/ext/modul-seltene/StructureDefinition/mii-pr-seltene-genetic-diagnosis",
              "http://hl7.org/fhir/StructureDefinition/Condition"
            ]
          }
        ],
        "mustSupport": true
      },
      {
        "id": "Extension.url",
        "path": "Extension.url",
        "fixedUri": "https://www.medizininformatik-initiative.de/fhir/ext/modul-seltene/StructureDefinition/mii-ex-seltene-tod-durch-seltene-erkrankung"
      },
      {
        "id": "Extension.value[x]",
        "path": "Extension.value[x]",
        "max": "0"
      }
    ]
  }
}
